kapture_localization/__init__.py
kapture_localization/evaluation.py
kapture_localization/colmap/__init__.py
kapture_localization/colmap/colmap_command.py
kapture_localization/colmap/pycolmap_command.py
kapture_localization/image_retrieval/__init__.py
kapture_localization/image_retrieval/fusion.py
kapture_localization/image_retrieval/pairing.py
kapture_localization/localization/DuplicateCorrespondencesStrategy.py
kapture_localization/localization/RerankCorrespondencesStrategy.py
kapture_localization/localization/__init__.py
kapture_localization/localization/correspondences.py
kapture_localization/localization/reprojection_error.py
kapture_localization/matching/__init__.py
kapture_localization/matching/matching.py
kapture_localization/pairing/__init__.py
kapture_localization/pairing/distance.py
kapture_localization/pairing/observations.py
kapture_localization/pairing/sequence.py
kapture_localization/pose_approximation/PoseApproximationMethods.py
kapture_localization/pose_approximation/__init__.py
kapture_localization/pose_approximation/pose_interpolation.py
kapture_localization/pose_approximation/weight_estimation.py
kapture_localization/triangulation/__init__.py
kapture_localization/triangulation/integration.py
kapture_localization/triangulation/triangulate.py
kapture_localization/utils/BenchmarkFormatStyle.py
kapture_localization/utils/__init__.py
kapture_localization/utils/cv_camera_matrix.py
kapture_localization/utils/logging.py
kapture_localization/utils/pairsfile.py
kapture_localization/utils/path_to_kapture.py
kapture_localization/utils/rigs_extension.py
kapture_localization/utils/subprocess.py
kapture_localization/utils/symlink.py
kapture_localization-1.1.10.data/data/README.adoc
kapture_localization-1.1.10.data/scripts/kapture_colmap_build_map.py
kapture_localization-1.1.10.data/scripts/kapture_colmap_build_sift_map.py
kapture_localization-1.1.10.data/scripts/kapture_colmap_localize.py
kapture_localization-1.1.10.dist-info/LICENSE
kapture_localization-1.1.10.dist-info/METADATA
kapture_localization-1.1.10.dist-info/NOTICE
kapture_localization-1.1.10.dist-info/WHEEL
kapture_localization-1.1.10.dist-info/top_level.txt
kapture_localization-1.1.10.dist-info/RECORD
