Metadata-Version: 2.1
Name: kapture-localization
Version: 1.1.10
Summary: kapture-localization: localization pipelines based on kapture.
Home-page: https://github.com/naver/kapture-localization/
Author: naverlabs
Author-email: kapture@naverlabs.com
Classifier: Programming Language :: Python :: 3
Classifier: License :: OSI Approved :: BSD License
Classifier: Operating System :: OS Independent
Requires-Python: >=3.8
License-File: LICENSE
License-File: NOTICE
Requires-Dist: kapture <1.2.0,>=1.1.10
Requires-Dist: numpy >=1.16
Requires-Dist: numpy-quaternion
Requires-Dist: numba
Requires-Dist: cvxpy >=1.1.6
Requires-Dist: torch >=1.4.0
Requires-Dist: tabulate >=0.8.7
Requires-Dist: opencv-python
Requires-Dist: build >=1.0.3
Provides-Extra: dev
Requires-Dist: pytest ; extra == 'dev'
